nrk_api/__init__.py
nrk_api/__main__.py
nrk_api/api.py
nrk_api/classes.py
nrk_api/cli.py
nrk_api/helpers.py
nrk_api/httpz.py
nrk_api/subtitle.py
nrk_api/version.py
nrk_api-0.0.2.dist-info/DESCRIPTION.rst
nrk_api-0.0.2.dist-info/METADATA
nrk_api-0.0.2.dist-info/RECORD
nrk_api-0.0.2.dist-info/WHEEL
nrk_api-0.0.2.dist-info/entry_points.txt
nrk_api-0.0.2.dist-info/metadata.json
nrk_api-0.0.2.dist-info/top_level.txt
