Metadata-Version: 2.0
Name: nrk-api
Version: 0.0.2
Summary: Download series or programs from NRK.
Home-page: https://github.com/Hellowlol/nrkdl
Author: hellowlol
Author-email: hellowlol1@gmail.com
License: GPL3
Requires-Dist: aiohttp (==2.1.0)
Requires-Dist: colorama
Requires-Dist: docopt
Requires-Dist: prompt-toolkit
Requires-Dist: requests (==2.17.3)
Requires-Dist: tqdm
Provides-Extra: dev
Requires-Dist: pypandoc; extra == 'dev'
Provides-Extra: test
Requires-Dist: codecov; extra == 'test'
Requires-Dist: pytest; extra == 'test'
Requires-Dist: pytest-cov; extra == 'test'
